sopt/__init__.py
sopt/GA/GA.py
sopt/GA/__init__.py
sopt/Optimizers/Gradients.py
sopt/Optimizers/RandomWalk.py
sopt/Optimizers/SA.py
sopt/Optimizers/__init__.py
sopt/PSO/PSO.py
sopt/PSO/__init__.py
sopt/SGA/SGA.py
sopt/SGA/__init__.py
sopt/test/__init__.py
sopt/test/test_AdaGrad.py
sopt/test/test_Adam.py
sopt/test/test_GA.py
sopt/test/test_GradientDescent.py
sopt/test/test_Momentum.py
sopt/test/test_PSO.py
sopt/test/test_RMSProp.py
sopt/test/test_RandomWalk.py
sopt/test/test_SA.py
sopt/test/test_SGA.py
sopt/util/__init__.py
sopt/util/constraints.py
sopt/util/functions.py
sopt/util/ga_config.py
sopt/util/gradients_config.py
sopt/util/pso_config.py
sopt/util/random_walk_config.py
sopt/util/sa_config.py
sopt-0.0.6.1.dist-info/DESCRIPTION.rst
sopt-0.0.6.1.dist-info/METADATA
sopt-0.0.6.1.dist-info/RECORD
sopt-0.0.6.1.dist-info/WHEEL
sopt-0.0.6.1.dist-info/metadata.json
sopt-0.0.6.1.dist-info/top_level.txt
